{
    "productList" : [
        {
            "id": 1,
			"nursery" : "Nursery 1",
            "plantName": "Monsterra",
			"plantSize": "small",
			"waterSchedule" : "morning",
			"color" : "green",
			"seasonal" : "winter",
			"lightEfficient" : true,
			"maintenance" : "Low maintenance",
            "plantType": "Indoor Plant",
            "image": "/product-image/1.jpeg",
            "productRating": "4",
            "price": 359,
            "salePrice": 299
        },
        {
            "id": 2,
			"nursery" : "Nursery 1",
            "plantName": "Monsterra",
			"plantSize": "medium",
			"waterSchedule" : "morning",
			"color" : "green",
			"seasonal" : "winter",
			"lightEfficient" : true,
            "maintenance" : "Low maintenance",
            "plantType": "Indoor Plant",
            "image": "/product-image/2.jpeg",
            "productRating": "4.5",
            "price": 359,
            "salePrice": 299
        },
        {
            "id": 3,
			"nursery" : "Nursery 1",
            "plantName": "Monsterra",
			"plantSize": "small",
			"waterSchedule" : "evening",
			"color" : "green",
			"seasonal" : "winter",
			"lightEfficient" : true,
            "maintenance" : "Low maintenance",
            "plantType": "Indoor Plant",
            "image": "/product-image/3.jpeg",
            "productRating": "5",
            "price": 359,
            "salePrice": 299
        },
        {
            "id": 4,
			"nursery" : "Nursery 2",
            "plantName": "Monsterra",
			"plantSize": "small",
			"waterSchedule" : "morning",
			"color" : "yellow",
			"seasonal" : "winter",
			"lightEfficient" : true,
            "maintenance" : "Low maintenance",
            "plantType": "Indoor Plant",
            "image": "/product-image/4.jpeg",
            "productRating": "3.5",
            "price": 359,
            "salePrice": 299
        },
        {
            "id": 5,
			"nursery" : "Nursery 2",
            "plantName": "Monsterra",
			"plantSize": "small",
			"waterSchedule" : "morning",
			"color" : "green",
			"seasonal" : "winter",
			"lightEfficient" : true,
            "maintenance" : "High maintenance",
            "plantType": "Indoor Plant",
            "image": "/product-image/5.jpeg",
            "productRating": "2.5",
            "price": 359,
            "salePrice": 299
        },
        {
            "id": 6,
			"nursery" : "Nursery 2",
            "plantName": "Monsterra",
			"plantSize": "small",
			"waterSchedule" : "morning",
			"color" : "green",
			"seasonal" : "winter",
			"lightEfficient" : true,
            "maintenance" : "Low maintenance",
            "plantType": "Outdoor Plant",
            "image": "/product-image/6.jpeg",
            "productRating": "3",
            "price": 359,
            "salePrice": 299
        },
        {
            "id": 7,
			"nursery" : "Nursery 3",
            "plantName": "Monsterra",
			"plantSize": "small",
			"waterSchedule" : "morning",
			"color" : "green",
			"seasonal" : "summer",
			"lightEfficient" : false,
            "maintenance" : "Low maintenance",
            "plantType": "Indoor Plant",
            "image": "/product-image/7.jpeg",
            "productRating": "5",
            "price": 359,
            "salePrice": 299
        },
        {
            "id": 8,
			"nursery" : "Nursery 3",
            "plantName": "Monsterra",
			"plantSize": "small",
			"waterSchedule" : "morning",
			"color" : "green",
			"seasonal" : "winter",
			"lightEfficient" : true,
            "maintenance" : "Low maintenance",
            "plantType": "Indoor Plant",
            "image": "/product-image/8.jpeg",
            "productRating": "4.5",
            "price": 359,
            "salePrice": 299
        },
        {
            "id": 9,
			"nursery" : "Nursery 3",
            "plantName": "Monsterra",
			"plantSize": "small",
			"waterSchedule" : "morning",
			"color" : "green",
			"seasonal" : "winter",
			"lightEfficient" : true,
            "maintenance" : "Low maintenance",
            "plantType": "Indoor Plant",
            "image": "/product-image/9.jpeg",
            "productRating": "4.5",
            "price": 359,
            "salePrice": 299
        },
        {
            "id": 10,
			"nursery" : "Nursery 4",
            "plantName": "Monsterra",
			"plantSize": "small",
			"waterSchedule" : "morning",
			"color" : "green",
			"seasonal" : "winter",
			"lightEfficient" : true,
            "maintenance" : "Low maintenance",
            "plantType": "Indoor Plant",
            "image": "/product-image/10.jpeg",
            "productRating": "4.5",
            "price": 359,
            "salePrice": 299
        },
        {
            "id": 11,
			"nursery" : "Nursery 4",
            "plantName": "Monsterra",
			"plantSize": "medium",
			"waterSchedule" : "morning",
			"color" : "green",
			"seasonal" : "winter",
			"lightEfficient" : true,
            "maintenance" : "Low maintenance",
            "plantType": "Indoor Plant",
            "image": "/product-image/11.jpeg",
            "productRating": "2.5",
            "price": 359,
            "salePrice": 299
        },
        {
            "id": 12,
			"nursery" : "Nursery 5",
            "plantName": "Monsterra",
			"plantSize": "large",
			"waterSchedule" : "morning",
			"color" : "green",
			"seasonal" : "summer",
			"lightEfficient" : true,
            "maintenance" : "Low maintenance",
            "plantType": "Outdoor Plant",
            "image": "/product-image/12.jpeg",
            "productRating": "4.5",
            "price": 359,
            "salePrice": 299
        },
        {
            "id": 13,
			"nursery" : "Nursery 5",
            "plantName": "Monsterra",
			"plantSize": "large",
			"waterSchedule" : "morning",
			"color" : "green",
			"seasonal" : "summer",
			"lightEfficient" : true,
            "maintenance" : "Low maintenance",
            "plantType": "Outdoor Plant",
            "image": "/product-image/12.jpeg",
            "productRating": "4.5",
            "price": 359,
            "salePrice": 299
        },
        {
            "id": 14,
			"nursery" : "Nursery 5",
            "plantName": "Monsterra",
			"plantSize": "large",
			"waterSchedule" : "morning",
			"color" : "green",
			"seasonal" : "summer",
			"lightEfficient" : true,
            "maintenance" : "Low maintenance",
            "plantType": "Outdoor Plant",
            "image": "/product-image/12.jpeg",
            "productRating": "4.5",
            "price": 359,
            "salePrice": 299
        },
        {
            "id": 15,
			"nursery" : "Nursery 5",
            "plantName": "Monsterra",
			"plantSize": "large",
			"waterSchedule" : "morning",
			"color" : "green",
			"seasonal" : "summer",
			"lightEfficient" : true,
            "maintenance" : "Low maintenance",
            "plantType": "Outdoor Plant",
            "image": "/product-image/12.jpeg",
            "productRating": "4.5",
            "price": 359,
            "salePrice": 299
        },
        {
            "id": 16,
			"nursery" : "Nursery 5",
            "plantName": "Monsterra",
			"plantSize": "large",
			"waterSchedule" : "morning",
			"color" : "green",
			"seasonal" : "summer",
			"lightEfficient" : true,
            "maintenance" : "Low maintenance",
            "plantType": "Outdoor Plant",
            "image": "/product-image/12.jpeg",
            "productRating": "4.5",
            "price": 359,
            "salePrice": 299
        },
        {
            "id": 17,
			"nursery" : "Nursery 5",
            "plantName": "Monsterra",
			"plantSize": "large",
			"waterSchedule" : "morning",
			"color" : "green",
			"seasonal" : "summer",
			"lightEfficient" : true,
            "maintenance" : "Low maintenance",
            "plantType": "Outdoor Plant",
            "image": "/product-image/12.jpeg",
            "productRating": "4.5",
            "price": 359,
            "salePrice": 299
        },
        {
            "id": 18,
			"nursery" : "Nursery 5",
            "plantName": "Monsterra",
			"plantSize": "large",
			"waterSchedule" : "morning",
			"color" : "green",
			"seasonal" : "summer",
			"lightEfficient" : true,
            "maintenance" : "Low maintenance",
            "plantType": "Outdoor Plant",
            "image": "/product-image/12.jpeg",
            "productRating": "4.5",
            "price": 359,
            "salePrice": 299
        },
        {
            "id": 19,
			"nursery" : "Nursery 5",
            "plantName": "Monsterra",
			"plantSize": "large",
			"waterSchedule" : "morning",
			"color" : "green",
			"seasonal" : "summer",
			"lightEfficient" : true,
            "maintenance" : "Low maintenance",
            "plantType": "Outdoor Plant",
            "image": "/product-image/12.jpeg",
            "productRating": "4.5",
            "price": 359,
            "salePrice": 299
        }
    ],
    "nurseryList" : [
        {
            "id": 1,
			"nurseryName" : "Nursery 1",
            "nurseryReview": "Lorem ipsum dolor sit amet. Aut ipsam illum et nostrum",
            "nurseryImage": "/nursery-image/1.png"
        },
        {
            "id": 2,
			"nurseryName" : "Nursery 2",
            "nurseryReview": "Lorem ipsum dolor sit amet. Aut ipsam illum et nostrum",
            "nurseryImage": "/nursery-image/2.png"
        },
        {
            "id": 3,
			"nurseryName" : "Nursery 3",
            "nurseryReview": "Lorem ipsum dolor sit amet. Aut ipsam illum et nostrum",
            "nurseryImage": "/nursery-image/3.png"
        },
        {
            "id": 4,
			"nurseryName" : "Nursery 4",
            "nurseryReview": "Lorem ipsum dolor sit amet. Aut ipsam illum et nostrum",
            "nurseryImage": "/nursery-image/4.png"
        },
        {
            "id": 5,
			"nurseryName" : "Nursery 5",
            "nurseryReview": "Lorem ipsum dolor sit amet. Aut ipsam illum et nostrum",
            "nurseryImage": "/nursery-image/5.png"
        }
    ]
}
